CoDIAC/AdjacencyFiles.py
CoDIAC/AlphaFold.py
CoDIAC/IntegrateStructure_Reference.py
CoDIAC/InterPro.py
CoDIAC/PDB.py
CoDIAC/PDBHelper.py
CoDIAC/PTM.py
CoDIAC/PhosphoSitePlus_Tools.py
CoDIAC/UniProt.py
CoDIAC/__init__.py
CoDIAC/alignmentTools.py
CoDIAC/config.py
CoDIAC/contactMap.py
CoDIAC/featureTools.py
CoDIAC/jalviewFunctions.py
CoDIAC/mutations.py
CoDIAC/pTyrLigand_helpers.py
CoDIAC/proteomeScoutAPI.py
CoDIAC/translateFeatures.py
CoDIAC/data/proteomescout_everything_20190701/citations.tsv
CoDIAC/data/proteomescout_everything_20190701/data.tsv
analysis/__init__.py
analysis/analysis.py
codiac-1.0.0.dist-info/licenses/LICENSE
codiac-1.0.0.dist-info/METADATA
codiac-1.0.0.dist-info/WHEEL
codiac-1.0.0.dist-info/entry_points.txt
codiac-1.0.0.dist-info/top_level.txt
codiac-1.0.0.dist-info/RECORD
